setup.py
juicepscheduler/Distributor.py
juicepscheduler/FileSystem.py
juicepscheduler/Scheduler Test.py
juicepscheduler/Scheduler.py
juicepscheduler/Settings.py
juicepscheduler/Worker.py
juicepscheduler/__init__.py
juicepscheduler.egg-info/PKG-INFO
juicepscheduler.egg-info/SOURCES.txt
juicepscheduler.egg-info/dependency_links.txt
juicepscheduler.egg-info/not-zip-safe
juicepscheduler.egg-info/top_level.txt