Metadata-Version: 1.0
Name: juicepscheduler
Version: 1.0
Summary: Juice Python Scheduler for scheduling tasks. On the basis of timestamp named files.
Home-page: https://bitbucket.org/Sahil-Gulati/juice-pscheduler
Author: Sahil Gulati
Author-email: sahil.gulati1991@outlook.com
License: UNKNOWN
Platform: UNKNOWN
